setup.py
klip/__init__.py
klip/devices.py
klip/parser.py
klip.egg-info/PKG-INFO
klip.egg-info/SOURCES.txt
klip.egg-info/dependency_links.txt
klip.egg-info/top_level.txt