Metadata-Version: 1.0
Name: klip
Version: 0.3
Summary: parse annotations/highlights from Amazon Kindle
Home-page: https://github.com/coolharsh55/klip
Author: Harshvardhan Pandit
Author-email: me@harshp.com
License: MIT
Platform: UNKNOWN
